pythonpackagetemplate/__init__.py
pythonpackagetemplate-0.1.5.dist-info/METADATA
pythonpackagetemplate-0.1.5.dist-info/RECORD
pythonpackagetemplate-0.1.5.dist-info/WHEEL
pythonpackagetemplate-0.1.5.dist-info/top_level.txt
