Metadata-Version: 2.1
Name: pythonpackagetemplate
Version: 0.1.5
Summary: Test python package with documentation and CI
Home-page: http://github.com/rutgerhofste/python_package_template
Author: Rutger Hofste
Author-email: rutgerhofste@gmail.com
License: MIT
Platform: UNKNOWN
Requires-Dist: pandas
